pybaker/__init__.py
pybaker/pybaker.py
pybaker-2.0.2.dist-info/LICENSE
pybaker-2.0.2.dist-info/METADATA
pybaker-2.0.2.dist-info/WHEEL
pybaker-2.0.2.dist-info/top_level.txt
pybaker-2.0.2.dist-info/RECORD
