Metadata-Version: 2.1
Name: pybaker
Version: 2.0.2
Summary: A build system library
Home-page: https://github.com/OatsLaBoats/pybaker
Author: oats
Author-email: chadriven12345@gmail.com
Project-URL: Bug Tracker, https://github.com/OatsLaBoats/pybaker/issues
Project-URL: repository, https://github.com/OatsLaBoats/pybaker
Classifier: Programming Language :: Python :: 3
Classifier: License :: OSI Approved :: MIT License
Classifier: Operating System :: OS Independent
Classifier: Topic :: Software Development :: Build Tools
Requires-Python: >=3.6
License-File: LICENSE
